[
  {
    "name": "_ga_KSM221PNDX",
    "value": "GS1.1.1743429983.1.1.1743430010.0.0.0",
    "domain": ".upwork.com",
    "path": "/",
    "expires": 1777990010.755627,
    "size": 51,
    "httpOnly": false,
    "secure": false,
    "session": false,
    "priority": "Medium",
    "sameParty": false,
    "sourceScheme": "Secure"
  },
  {
    "name": "AWSALBCORS",
    "value": "AkU4jZRc1nLgIUwXv0pxYymnIqzkFiuW5JfQb+aJklDcGYDq81c2CBkN5ePdsOaf7tQqsy+DYmJt0Hm0T2WHLoAi8Mj3gJZx0+l1GYDWi1OrBlvxk2cC454FvIG3",
    "domain": "www.upwork.com",
    "path": "/",
    "expires": 1744034810.708761,
    "size": 134,
    "httpOnly": false,
    "secure": true,
    "session": false,
    "sameSite": "None",
    "priority": "Medium",
    "sameParty": false,
    "sourceScheme": "Secure"
  },
  {
    "name": "AWSALB",
    "value": "AkU4jZRc1nLgIUwXv0pxYymnIqzkFiuW5JfQb+aJklDcGYDq81c2CBkN5ePdsOaf7tQqsy+DYmJt0Hm0T2WHLoAi8Mj3gJZx0+l1GYDWi1OrBlvxk2cC454FvIG3",
    "domain": "www.upwork.com",
    "path": "/",
    "expires": 1744034810.708584,
    "size": 130,
    "httpOnly": false,
    "secure": false,
    "session": false,
    "priority": "Medium",
    "sameParty": false,
    "sourceScheme": "Secure"
  },
  {
    "name": "forterToken",
    "value": "743b3ac4e3ec4975a3d513781d9ce6b5_1743430008588__UDF43-m4_23ck_oH7HIQh6oNA%3D-1290-v2",
    "domain": ".upwork.com",
    "path": "/",
    "expires": 1777990010,
    "size": 95,
    "httpOnly": false,
    "secure": false,
    "session": false,
    "priority": "Medium",
    "sameParty": false,
    "sourceScheme": "Secure"
  },
  {
    "name": "asct_vt",
    "value": "oauth2v2_e9a529d4686c99e415df78777a55e069",
    "domain": ".upwork.com",
    "path": "/",
    "expires": 1743516377.770332,
    "size": 48,
    "httpOnly": false,
    "secure": true,
    "session": false,
    "priority": "Medium",
    "sameParty": false,
    "sourceScheme": "Secure"
  },
  {
    "name": "AWSALBTGCORS",
    "value": "T+y88iMHzkELqicdv7UL5krFe7KebpPSJbjbdrprOcvIgm/XnAAx6EQeY8HsvtrWXmsmHlH+1ETng9j2VO0/CsH1SwxAtMPo223C5STecTYJ+Q2qP3NXauVV9eJaK8zJ5/g4S/3vRLcQIEMtrF1Cs34lrv+GWwcMG2LfStf52iJq",
    "domain": "www.upwork.com",
    "path": "/",
    "expires": 1744034809.068468,
    "size": 184,
    "httpOnly": false,
    "secure": true,
    "session": false,
    "sameSite": "None",
    "priority": "Medium",
    "sameParty": false,
    "sourceScheme": "Secure"
  },
  {
    "name": "_ttp",
    "value": "01JQP8DG3V3MZ6C622S13J78TP_.tt.1",
    "domain": ".upwork.com",
    "path": "/",
    "expires": 1777126008,
    "size": 36,
    "httpOnly": false,
    "secure": false,
    "session": false,
    "priority": "Medium",
    "sameParty": false,
    "sourceScheme": "Secure"
  },
  {
    "name": "_tt_enable_cookie",
    "value": "1",
    "domain": ".upwork.com",
    "path": "/",
    "expires": 1777126008,
    "size": 18,
    "httpOnly": false,
    "secure": false,
    "session": false,
    "priority": "Medium",
    "sameParty": false,
    "sourceScheme": "Secure"
  },
  {
    "name": "OptanonConsent",
    "value": "isGpcEnabled=0&datestamp=Mon+Mar+31+2025+17%3A36%3A45+GMT%2B0330+(Iran+Standard+Time)&version=202305.1.0&browserGpcFlag=0&isIABGlobal=false&hosts=&consentId=40a431c8-e4a6-4dd9-93a6-46d357b41f7f&interactionCount=1&landingPath=NotLandingPage&groups=C0001%3A1%2CC0002%3A1%2CC0003%3A1%2CC0004%3A1&AwaitingReconsent=false",
    "domain": ".upwork.com",
    "path": "/",
    "expires": 1774966005,
    "size": 330,
    "httpOnly": false,
    "secure": false,
    "session": false,
    "sameSite": "Lax",
    "priority": "Medium",
    "sameParty": false,
    "sourceScheme": "Secure"
  },
  {
    "name": "_ga",
    "value": "GA1.1.700522759.1743429984",
    "domain": ".upwork.com",
    "path": "/",
    "expires": 1777990010.756565,
    "size": 29,
    "httpOnly": false,
    "secure": false,
    "session": false,
    "priority": "Medium",
    "sameParty": false,
    "sourceScheme": "Secure"
  },
  {
    "name": "5af05c94sb",
    "value": "oauth2v2_bd1a66d38e76c2f5321cdd897fd1d006",
    "domain": ".upwork.com",
    "path": "/",
    "expires": 1743516400.310976,
    "size": 51,
    "httpOnly": true,
    "secure": true,
    "session": false,
    "priority": "Medium",
    "sameParty": false,
    "sourceScheme": "Secure"
  },
  {
    "name": "company_last_accessed",
    "value": "d28102646",
    "domain": ".upwork.com",
    "path": "/",
    "expires": 1746108401.024447,
    "size": 30,
    "httpOnly": false,
    "secure": false,
    "session": false,
    "priority": "Medium",
    "sameParty": false,
    "sourceScheme": "Secure"
  },
  {
    "name": "master_access_token",
    "value": "44b115b8.oauth2v2_d4697bf0dccd71ae63bf9483fd903f22",
    "domain": ".upwork.com",
    "path": "/",
    "expires": -1,
    "size": 69,
    "httpOnly": true,
    "secure": false,
    "session": true,
    "priority": "Medium",
    "sameParty": false,
    "sourceScheme": "Secure"
  },
  {
    "name": "user_uid",
    "value": "1185868123840708608",
    "domain": ".upwork.com",
    "path": "/",
    "expires": -1,
    "size": 27,
    "httpOnly": true,
    "secure": false,
    "session": true,
    "priority": "Medium",
    "sameParty": false,
    "sourceScheme": "Secure"
  },
  {
    "name": "uTheme",
    "value": "dark",
    "domain": ".upwork.com",
    "path": "/",
    "expires": 1746108402.310758,
    "size": 10,
    "httpOnly": false,
    "secure": true,
    "session": false,
    "priority": "Medium",
    "sameParty": false,
    "sourceScheme": "Secure"
  },
  {
    "name": "cf_clearance",
    "value": "w.0iB3BHw92.cONRZ19RWsUIsbg.Xu6E_O9BmRR0zRw-1743429977-1.2.1.1-nbKV3tjIWG4PLYYkybKMr1Vv6tHV0zlOF3q.__e6S4_u_Hk3Q2mTC_g0TLLuy._9zWwhXrFhXTi3UmfTwE3Y4GZdguGrluSy53wFHeY..y6S38cHoMk51V7SPSQLLPCnKpKXQiOAlIIfLEr9ZWc2asoDCIhDxL1Oz4BYbRffSJvAvuZJnn.g4iYi7sprxj5UFPiM5GtJUM8q8OXdClhc2WuqHoYAHpAhcua_mUPBZxD.on1EAA44OhfIVu7dwH3b9tAmb2AZ2JLyPdoOH9.ClYHddnfK1jGJaBhNLKXkTLoL.bY.azCBe9i3Zt8mOSpm4SX2dvmS7wSvqg7HehibqIf.4oPGQXX6EIOCcAcC4hE",
    "domain": ".upwork.com",
    "path": "/",
    "expires": 1774965977.725963,
    "size": 438,
    "httpOnly": true,
    "secure": true,
    "session": false,
    "sameSite": "None",
    "priority": "Medium",
    "sameParty": false,
    "sourceScheme": "Secure",
    "partitionKey": "https://upwork.com"
  },
  {
    "name": "console_user",
    "value": "farvimgh",
    "domain": ".upwork.com",
    "path": "/",
    "expires": -1,
    "size": 20,
    "httpOnly": true,
    "secure": false,
    "session": true,
    "priority": "Medium",
    "sameParty": false,
    "sourceScheme": "Secure"
  },
  {
    "name": "spt",
    "value": "30850044-73b5-446f-9919-711234c2b958",
    "domain": ".upwork.com",
    "path": "/",
    "expires": 1774966010.708911,
    "size": 39,
    "httpOnly": true,
    "secure": true,
    "session": false,
    "sameSite": "None",
    "priority": "Medium",
    "sameParty": false,
    "sourceScheme": "Secure"
  },
  {
    "name": "recognized",
    "value": "farvimgh",
    "domain": ".upwork.com",
    "path": "/",
    "expires": 1753430001.024067,
    "size": 18,
    "httpOnly": false,
    "secure": false,
    "session": false,
    "priority": "Medium",
    "sameParty": false,
    "sourceScheme": "Secure"
  },
  {
    "name": "IR_gbd",
    "value": "upwork.com",
    "domain": ".upwork.com",
    "path": "/",
    "expires": -1,
    "size": 16,
    "httpOnly": false,
    "secure": false,
    "session": true,
    "priority": "Medium",
    "sameParty": false,
    "sourceScheme": "Secure"
  },
  {
    "name": "_gcl_au",
    "value": "1.1.993826463.1743429978",
    "domain": ".upwork.com",
    "path": "/",
    "expires": 1751205978,
    "size": 31,
    "httpOnly": false,
    "secure": false,
    "session": false,
    "priority": "Medium",
    "sameParty": false,
    "sourceScheme": "Secure"
  },
  {
    "name": "DA_farvimgh",
    "value": "df6861597b8effbc95b986fc1ce7a23d11f17bc5edc33b08569fa0ba037f336f",
    "domain": ".upwork.com",
    "path": "/",
    "expires": 1751206001.02428,
    "size": 75,
    "httpOnly": true,
    "secure": false,
    "session": false,
    "priority": "Medium",
    "sameParty": false,
    "sourceScheme": "Secure"
  },
  {
    "name": "__podscribe_did",
    "value": "pscrb_ce4820ba-04a2-40af-aea4-615a76855529",
    "domain": ".upwork.com",
    "path": "/",
    "expires": 1774965984,
    "size": 57,
    "httpOnly": false,
    "secure": true,
    "session": false,
    "sameSite": "None",
    "priority": "Medium",
    "sameParty": false,
    "sourceScheme": "Secure"
  },
  {
    "name": "__podscribe_upwork_landing_url",
    "value": "https://www.upwork.com/ab/account-security/login",
    "domain": ".upwork.com",
    "path": "/",
    "expires": 1774965984,
    "size": 78,
    "httpOnly": false,
    "secure": true,
    "session": false,
    "sameSite": "None",
    "priority": "Medium",
    "sameParty": false,
    "sourceScheme": "Secure"
  },
  {
    "name": "G_ENABLED_IDPS",
    "value": "google",
    "domain": ".www.upwork.com",
    "path": "/",
    "expires": 1777989979.925652,
    "size": 20,
    "httpOnly": false,
    "secure": false,
    "session": false,
    "priority": "Medium",
    "sameParty": false,
    "sourceScheme": "Secure"
  },
  {
    "name": "__podscribe_upwork_referrer",
    "value": "_",
    "domain": ".upwork.com",
    "path": "/",
    "expires": 1774965984,
    "size": 28,
    "httpOnly": false,
    "secure": true,
    "session": false,
    "sameSite": "None",
    "priority": "Medium",
    "sameParty": false,
    "sourceScheme": "Secure"
  },
  {
    "name": "SZ",
    "value": "78446f2bf3fda77e5850aea9bd083987b7305551525e58041957b686656d61f3",
    "domain": ".upwork.com",
    "path": "/",
    "expires": -1,
    "size": 66,
    "httpOnly": true,
    "secure": false,
    "session": true,
    "priority": "Medium",
    "sameParty": false,
    "sourceScheme": "Secure"
  },
  {
    "name": "IR_13634",
    "value": "1743430010676%7C0%7C1743430010676%7C%7C",
    "domain": ".upwork.com",
    "path": "/",
    "expires": -1,
    "size": 47,
    "httpOnly": false,
    "secure": true,
    "session": true,
    "priority": "Medium",
    "sameParty": false,
    "sourceScheme": "Secure"
  },
  {
    "name": "_uetsid",
    "value": "542414b00e3911f0b98fc526da1668d9",
    "domain": "www.upwork.com",
    "path": "/",
    "expires": 1743516410,
    "size": 39,
    "httpOnly": false,
    "secure": false,
    "session": false,
    "priority": "Medium",
    "sameParty": false,
    "sourceScheme": "Secure"
  },
  {
    "name": "AWSALBTG",
    "value": "T+y88iMHzkELqicdv7UL5krFe7KebpPSJbjbdrprOcvIgm/XnAAx6EQeY8HsvtrWXmsmHlH+1ETng9j2VO0/CsH1SwxAtMPo223C5STecTYJ+Q2qP3NXauVV9eJaK8zJ5/g4S/3vRLcQIEMtrF1Cs34lrv+GWwcMG2LfStf52iJq",
    "domain": "www.upwork.com",
    "path": "/",
    "expires": 1744034809.068116,
    "size": 180,
    "httpOnly": false,
    "secure": false,
    "session": false,
    "priority": "Medium",
    "sameParty": false,
    "sourceScheme": "Secure"
  },
  {
    "name": "oauth2_global_js_token",
    "value": "oauth2v2_82b4dd1cf4d51bea404e4c5d71bca883",
    "domain": ".upwork.com",
    "path": "/",
    "expires": -1,
    "size": 63,
    "httpOnly": false,
    "secure": false,
    "session": true,
    "priority": "Medium",
    "sameParty": false,
    "sourceScheme": "Secure"
  },
  {
    "name": "_upw_id.5831",
    "value": "05e632ff-3b6a-412a-90fb-b8ddc613a094.1743429978.1.1743430010..f493ce4a-4fe3-426b-9ec4-5c927b693fb0..37d8dc7a-4b22-4816-85c5-9a7cb419a3bf.1743429978122.21",
    "domain": ".upwork.com",
    "path": "/",
    "expires": 1777990010.2976,
    "size": 165,
    "httpOnly": false,
    "secure": true,
    "session": false,
    "sameSite": "None",
    "priority": "Medium",
    "sameParty": false,
    "sourceScheme": "Secure"
  },
  {
    "name": "__cf_bm",
    "value": "OIssulUT4k2OmErs6X5HebCbIP8xZ1UVat4OoP1AiFw-1743429975-1.0.1.1-PjjBiJKxDU0tAWn38h5mTN5YMik9NDCFU8Ibn7Q66nAi7q1F.2AksiK2m1LoS2ZnZz0SFdfsxckZzTMZWtYPseL5MKFI_iGURq_pBSDoino",
    "domain": ".upwork.com",
    "path": "/",
    "expires": 1743431776.102731,
    "size": 177,
    "httpOnly": true,
    "secure": true,
    "session": false,
    "sameSite": "None",
    "priority": "Medium",
    "sameParty": false,
    "sourceScheme": "Secure"
  },
  {
    "name": "_fbp",
    "value": "fb.1.1743429983082.695549452605671478",
    "domain": ".upwork.com",
    "path": "/",
    "expires": 1751206010,
    "size": 41,
    "httpOnly": false,
    "secure": false,
    "session": false,
    "sameSite": "Lax",
    "priority": "Medium",
    "sameParty": false,
    "sourceScheme": "Secure"
  },
  {
    "name": "forterToken",
    "value": "743b3ac4e3ec4975a3d513781d9ce6b5_1743430008588__UDF43-m4_23ck_oH7HIQh6oNA%3D-1290-v2",
    "domain": ".www.upwork.com",
    "path": "/",
    "expires": 1777990010,
    "size": 95,
    "httpOnly": false,
    "secure": false,
    "session": false,
    "priority": "Medium",
    "sameParty": false,
    "sourceScheme": "Secure"
  },
  {
    "name": "uThemeMode",
    "value": "dark",
    "domain": ".upwork.com",
    "path": "/",
    "expires": 1746108402.310805,
    "size": 14,
    "httpOnly": false,
    "secure": true,
    "session": false,
    "priority": "Medium",
    "sameParty": false,
    "sourceScheme": "Secure"
  },
  {
    "name": "_cq_duid",
    "value": "1.1743429981.h2isUbqDeZo5Xk75",
    "domain": ".upwork.com",
    "path": "/",
    "expires": 1751314006,
    "size": 37,
    "httpOnly": false,
    "secure": true,
    "session": false,
    "sameSite": "None",
    "priority": "Medium",
    "sameParty": false,
    "sourceScheme": "Secure"
  },
  {
    "name": "country_code",
    "value": "OM",
    "domain": ".upwork.com",
    "path": "/",
    "expires": -1,
    "size": 14,
    "httpOnly": false,
    "secure": true,
    "session": true,
    "priority": "Medium",
    "sameParty": false,
    "sourceScheme": "Secure"
  },
  {
    "name": "cookie_domain",
    "value": ".upwork.com",
    "domain": "www.upwork.com",
    "path": "/",
    "expires": -1,
    "size": 24,
    "httpOnly": false,
    "secure": true,
    "session": true,
    "priority": "Medium",
    "sameParty": false,
    "sourceScheme": "Secure"
  },
  {
    "name": "IR_PI",
    "value": "54dc16ca-0e39-11f0-a306-75eddef5d75b%7C1743429983842",
    "domain": ".upwork.com",
    "path": "/",
    "expires": 1777989985.151109,
    "size": 57,
    "httpOnly": false,
    "secure": true,
    "session": false,
    "priority": "Medium",
    "sameParty": false,
    "sourceScheme": "Secure"
  },
  {
    "name": "umq",
    "value": "1280",
    "domain": ".upwork.com",
    "path": "/",
    "expires": 1758981977.286396,
    "size": 7,
    "httpOnly": false,
    "secure": true,
    "session": false,
    "priority": "Medium",
    "sameParty": false,
    "sourceScheme": "Secure"
  },
  {
    "name": "visitor_id",
    "value": "154.205.147.80.1743429975440000",
    "domain": ".upwork.com",
    "path": "/",
    "expires": 1774966001.024487,
    "size": 41,
    "httpOnly": false,
    "secure": false,
    "session": false,
    "priority": "Medium",
    "sameParty": false,
    "sourceScheme": "Secure"
  },
  {
    "name": "__cflb",
    "value": "02DiuEXPXZVk436fJfSVuuwDqLqkhavJbcPQD1W5JDfvT",
    "domain": "www.upwork.com",
    "path": "/",
    "expires": 1744034776.102871,
    "size": 51,
    "httpOnly": true,
    "secure": true,
    "session": false,
    "sameSite": "None",
    "priority": "Medium",
    "sameParty": false,
    "sourceScheme": "Secure"
  },
  {
    "name": "_cfuvid",
    "value": "9_HvByjBOSHmFgwMENoW6WKIGp5qe4pdfr54pkdSIJw-1743429975826-0.0.1.1-604800000",
    "domain": ".upwork.com",
    "path": "/",
    "expires": -1,
    "size": 82,
    "httpOnly": true,
    "secure": true,
    "session": true,
    "sameSite": "None",
    "priority": "Medium",
    "sameParty": false,
    "sourceScheme": "Secure"
  },
  {
    "name": "__pdst",
    "value": "fd13c034a4e54745849417100a95aaa4",
    "domain": "www.upwork.com",
    "path": "/",
    "expires": 1774965983,
    "size": 38,
    "httpOnly": false,
    "secure": false,
    "session": false,
    "sameSite": "Strict",
    "priority": "Medium",
    "sameParty": false,
    "sourceScheme": "Secure"
  },
  {
    "name": "current_organization_uid",
    "value": "1185868123865874433",
    "domain": ".upwork.com",
    "path": "/",
    "expires": 1746108402.310896,
    "size": 43,
    "httpOnly": false,
    "secure": true,
    "session": false,
    "priority": "Medium",
    "sameParty": false,
    "sourceScheme": "Secure"
  },
  {
    "name": "enabled_ff",
    "value": "!CI10270Air2Dot5QTAllocations,!CI10857Air3Dot0,!CI12577UniversalSearch,!MP16400Air3Migration,!RMTAir3Hired,!RMTAir3Home,!RMTAir3Offer,!RMTAir3Offers,!RMTAir3Talent,!SSINavUser,!SecAIBnrOn,!air2Dot76Qt,!i18nGA,CI11132Air2Dot75,CI17409DarkModeUI,CI9570Air2Dot5,JPAir3,OTBnrOn,SSINavUserBpa,TONB2256Air3Migration,air2Dot76,i18nOn",
    "domain": "www.upwork.com",
    "path": "/",
    "expires": -1,
    "size": 336,
    "httpOnly": false,
    "secure": true,
    "session": true,
    "priority": "Medium",
    "sameParty": false,
    "sourceScheme": "Secure"
  },
  {
    "name": "_rdt_uuid",
    "value": "1743429983113.e5d43f53-5326-40d9-abfa-31630a206310",
    "domain": ".upwork.com",
    "path": "/",
    "expires": 1751206010,
    "size": 59,
    "httpOnly": false,
    "secure": true,
    "session": false,
    "sameSite": "Strict",
    "priority": "Medium",
    "sameParty": false,
    "sourceScheme": "Secure"
  },
  {
    "name": "_cq_suid",
    "value": "1.1743429981.LWonOQvz1CV22u7L",
    "domain": ".upwork.com",
    "path": "/",
    "expires": -1,
    "size": 37,
    "httpOnly": false,
    "secure": true,
    "session": true,
    "sameSite": "None",
    "priority": "Medium",
    "sameParty": false,
    "sourceScheme": "Secure"
  },
  {
    "name": "_upw_ses.5831",
    "value": "*",
    "domain": ".upwork.com",
    "path": "/",
    "expires": 1743431810,
    "size": 14,
    "httpOnly": false,
    "secure": true,
    "session": false,
    "sameSite": "None",
    "priority": "Medium",
    "sameParty": false,
    "sourceScheme": "Secure"
  },
  {
    "name": "_uetvid",
    "value": "542452200e3911f0a3ea413f4c9b6b9b",
    "domain": "www.upwork.com",
    "path": "/",
    "expires": 1777126010,
    "size": 39,
    "httpOnly": false,
    "secure": false,
    "session": false,
    "priority": "Medium",
    "sameParty": false,
    "sourceScheme": "Secure"
  },
  {
    "name": "_gcl_au",
    "value": "1.1.993826463.1743429978",
    "domain": "www.upwork.com",
    "path": "/",
    "expires": 1751205978,
    "size": 31,
    "httpOnly": false,
    "secure": false,
    "session": false,
    "priority": "Medium",
    "sameParty": false,
    "sourceScheme": "Secure"
  },
  {
    "name": "cookie_prefix",
    "value": "",
    "domain": "www.upwork.com",
    "path": "/",
    "expires": -1,
    "size": 13,
    "httpOnly": false,
    "secure": true,
    "session": true,
    "priority": "Medium",
    "sameParty": false,
    "sourceScheme": "Secure"
  },
  {
    "name": "XSRF-TOKEN",
    "value": "5188036cd6f81528cc9f734ce57f07cd",
    "domain": ".upwork.com",
    "path": "/",
    "expires": -1,
    "size": 42,
    "httpOnly": false,
    "secure": true,
    "session": true,
    "priority": "Medium",
    "sameParty": false,
    "sourceScheme": "Secure"
  },
  {
    "name": "b5c63b5asb",
    "value": "oauth2v2_b2c29c2abdec9532161d846c5a7df5b8",
    "domain": ".upwork.com",
    "path": "/nx/find-work/",
    "expires": 1743516401.310851,
    "size": 51,
    "httpOnly": true,
    "secure": true,
    "session": false,
    "priority": "Medium",
    "sameParty": false,
    "sourceScheme": "Secure"
  }
]